LICENSE
MANIFEST.in
README.rst
setup.py
./url_images/__init__.py
./url_images/cache.py
./url_images/exceptions.py
./url_images/models.py
./url_images/mods.py
./url_images/response_backends.py
./url_images/tests.py
./url_images/urls.py
python_url_images.egg-info/PKG-INFO
python_url_images.egg-info/SOURCES.txt
python_url_images.egg-info/dependency_links.txt
python_url_images.egg-info/top_level.txt