Metadata-Version: 1.0
Name: python-url-images
Version: 0.0.1
Summary: URL-based manipulation of images
Home-page: https://github.com/AndrewIngram/python-url-images
Author: Andrew Ingram
Author-email: andy@andrewingram.net
License: MIT
Platform: UNKNOWN
Classifier: Development Status :: 3 - Alpha
Classifier: Environment :: Web Environment
Classifier: Intended Audience :: Developers
Classifier: Programming Language :: Python
